
 <databaseChangeLog
    xmlns="http://www.liquibase.org/xml/ns/dbchangelog"
    xmlns:xsi="http://www.w3.org/2001/XMLSchema-instance"
    xmlns:ext="http://www.liquibase.org/xml/ns/dbchangelog-ext"
    xmlns:pro="http://www.liquibase.org/xml/ns/pro"
    xsi:schemaLocation="http://www.liquibase.org/xml/ns/dbchangelog
        http://www.liquibase.org/xml/ns/dbchangelog/dbchangelog-latest.xsd
        http://www.liquibase.org/xml/ns/dbchangelog-ext http://www.liquibase.org/xml/ns/dbchangelog/dbchangelog-ext.xsd
        http://www.liquibase.org/xml/ns/pro http://www.liquibase.org/xml/ns/pro/liquibase-pro-latest.xsd">

<property name="schema_name" value="restaurant"/>

 <!-- add foreignkey now -->

    
<!-- adding for model evenement -->
 <changeSet author="fayssol" id="EVENT-FOREIGNKEY-RESTO001">
        <addForeignKeyConstraint baseTableSchemaName="${schema_name}" baseColumnNames="restaurant_id" 
                                 baseTableName="evenements" constraintName="evenements_resto_fk" deferrable="false" 
                                 initiallyDeferred="false" onDelete="NO ACTION" onUpdate="NO ACTION" referencedColumnNames="code"
                                 referencedTableName="restaurants" referencedTableSchemaName="${schema_name}"/>
    </changeSet>

    <!-- adding for modal pub -->
    <changeSet author="fayssol" id="PUB-FOREIGNKEY-RESTO001">
        <addForeignKeyConstraint baseTableSchemaName="${schema_name}" baseColumnNames="restaurant_id" 
                                 baseTableName="publicites" constraintName="publicites_resto_fk" deferrable="false" 
                                 initiallyDeferred="false" onDelete="NO ACTION" onUpdate="NO ACTION" referencedColumnNames="code"
                                 referencedTableName="restaurants" referencedTableSchemaName="${schema_name}"/>
    </changeSet>
     
    <!-- adding for model adhesion -->

     <changeSet author="fayssol" id="ADHESION-FOREIGNKEY-RESTO001">
        <addForeignKeyConstraint baseTableSchemaName="${schema_name}" baseColumnNames="restaurant_id" 
                                 baseTableName="adhesions" constraintName="adhesions_resto_fk" deferrable="false" 
                                 initiallyDeferred="false" onDelete="NO ACTION" onUpdate="NO ACTION" referencedColumnNames="code"
                                 referencedTableName="restaurants" referencedTableSchemaName="${schema_name}"/>
    </changeSet>
 </databaseChangeLog>